<?xml version="1.0" encoding="UTF-8"?><logs xmlns="http://www.witsml.org/schemas/1series" xmlns:xsi="http://www.w3.org/2001/XMLSchema-instance" version="1.4.1.1"><log uidWell="5da3aeeb-12c9-4732-a059-e3a8d7c32442" uidWellbore="eba2d47b-95f4-468f-856c-32c72d706a96" uid="68VFNI35"><nameWell>NO 15/9-F-7</nameWell><nameWellbore>NO 15/9-F-7</nameWellbore><name>GenTime</name><objectGrowing>false</objectGrowing><serviceCompany>Baker Hughes</serviceCompany><runNumber>1</runNumber><pass>0</pass><creationDate>2016-07-28T10:57:33.600Z</creationDate><description>Data Log</description><indexType>date time</indexType><startDateTimeIndex>2016-07-30T01:51:29.000Z</startDateTimeIndex><endDateTimeIndex>2016-07-30T01:55:13.000Z</endDateTimeIndex><direction>increasing</direction><indexCurve>Time</indexCurve><nullValue>-999.25</nullValue><priv_dTimPriority>2016-07-28T10:57:33.600Z</priv_dTimPriority><logCurveInfo uid="FLOWOUTPC"><mnemonic>FLOWOUTPC</mnemonic><classWitsml>flowOutPc</classWitsml><unit>Euc</unit><mnemAlias>FLOWOUTPC</mnemAlias><minDateTimeIndex>2016-07-30T01:51:29.000Z</minDateTimeIndex><maxDateTimeIndex>2016-07-30T01:55:13.000Z</maxDateTimeIndex><curveDescription>Mud Flow Out Percent</curveDescription><typeLogData>double</typeLogData></logCurveInfo><logCurveInfo uid="FLOWOUT"><mnemonic>FLOWOUT</mnemonic><classWitsml>flowOutAv</classWitsml><unit>m3/s</unit><mnemAlias>FLOWOUT</mnemAlias><minDateTimeIndex>2016-07-30T01:51:29.000Z</minDateTimeIndex><maxDateTimeIndex>2016-07-30T01:55:13.000Z</maxDateTimeIndex><curveDescription>Mud Flow Out</curveDescription><typeLogData>double</typeLogData></logCurveInfo><logCurveInfo uid="MOTOR_RPM"><mnemonic>MOTOR_RPM</mnemonic><classWitsml>mmrpm</classWitsml><unit>c/s</unit><mnemAlias>MOTOR_RPM</mnemAlias><minDateTimeIndex>2016-07-30T01:51:29.000Z</minDateTimeIndex><maxDateTimeIndex>2016-07-30T01:55:13.000Z</maxDateTimeIndex><curveDescription>Motor RPM</curveDescription><typeLogData>double</typeLogData></logCurveInfo><logCurveInfo uid="PITTOT"><mnemonic>PITTOT</mnemonic><classWitsml>tvol</classWitsml><unit>m3</unit><mnemAlias>PITTOT</mnemAlias><minDateTimeIndex>2016-07-30T01:51:29.000Z</minDateTimeIndex><maxDateTimeIndex>2016-07-30T01:55:13.000Z</maxDateTimeIndex><curveDescription>Total Pit Volume</curveDescription><typeLogData>double</typeLogData></logCurveInfo><logCurveInfo uid="MIN_2M"><mnemonic>MIN_2M</mnemonic><unit>s</unit><mnemAlias>MIN_2M</mnemAlias><minDateTimeIndex>2016-07-30T01:51:29.000Z</minDateTimeIndex><maxDateTimeIndex>2016-07-30T01:55:13.000Z</maxDateTimeIndex><curveDescription>Minutes/last 2 m</curveDescription><typeLogData>double</typeLogData></logCurveInfo><logCurveInfo uid="KILL_HIGH"><mnemonic>KILL_HIGH</mnemonic><unit>Pa</unit><mnemAlias>KILL_HIGH</mnemAlias><minDateTimeIndex>2016-07-30T01:51:29.000Z</minDateTimeIndex><maxDateTimeIndex>2016-07-30T01:55:13.000Z</maxDateTimeIndex><curveDescription>Kill Pressure</curveDescription><typeLogData>double</typeLogData></logCurveInfo><logCurveInfo uid="RigActivityCode"><mnemonic>RigActivityCode</mnemonic><unit>unitless</unit><mnemAlias>RigActivityCode</mnemAlias><minDateTimeIndex>2016-07-30T01:51:29.000Z</minDateTimeIndex><maxDateTimeIndex>2016-07-30T01:55:13.000Z</maxDateTimeIndex><curveDescription>NoMonitor[0] Drilling[1] Reaming[2] OffBottom[3] InSlips[4] Connection[5] TrippingIn[6] TrippingOut[7] TripInSlips[8] ShutIn[9] Circulating (10) Rotating (100) -  112 means rotating, circulating, reaming, 013 means not rotating, circulating, off bottom .</curveDescription><typeLogData>long</typeLogData></logCurveInfo><logCurveInfo uid="TORQUE_MAX"><mnemonic>TORQUE_MAX</mnemonic><unit>N.m</unit><mnemAlias>TORQUE_MAX</mnemAlias><minDateTimeIndex>2016-07-30T01:51:29.000Z</minDateTimeIndex><maxDateTimeIndex>2016-07-30T01:55:13.000Z</maxDateTimeIndex><curveDescription>Surface Torque Average</curveDescription><typeLogData>double</typeLogData></logCurveInfo><logCurveInfo uid="MSE"><mnemonic>MSE</mnemonic><unit>Pa</unit><mnemAlias>MSE</mnemAlias><minDateTimeIndex>2016-07-30T01:51:29.000Z</minDateTimeIndex><maxDateTimeIndex>2016-07-30T01:55:13.000Z</maxDateTimeIndex><curveDescription>Mechanical Specific Energy</curveDescription><typeLogData>double</typeLogData></logCurveInfo><logCurveInfo uid="ONBOTTOM_TIME"><mnemonic>ONBOTTOM_TIME</mnemonic><classWitsml>cTimBit</classWitsml><unit>s</unit><mnemAlias>ONBOTTOM_TIME</mnemAlias><minDateTimeIndex>2016-07-30T01:51:29.000Z</minDateTimeIndex><maxDateTimeIndex>2016-07-30T01:55:13.000Z</maxDateTimeIndex><curveDescription>Cumulative On-Bottom Time</curveDescription><typeLogData>double</typeLogData></logCurveInfo><logCurveInfo uid="RIGHEAVE"><mnemonic>RIGHEAVE</mnemonic><unit>unitless</unit><mnemAlias>RIGHEAVE</mnemAlias><minDateTimeIndex>2016-07-30T01:51:29.000Z</minDateTimeIndex><maxDateTimeIndex>2016-07-30T01:55:13.000Z</maxDateTimeIndex><curveDescription>Rig Heave</curveDescription><typeLogData>double</typeLogData></logCurveInfo><logCurveInfo uid="EditFlag"><mnemonic>EditFlag</mnemonic><unit>unitless</unit><mnemAlias>EditFlag</mnemAlias><minDateTimeIndex>2016-07-30T01:51:29.000Z</minDateTimeIndex><maxDateTimeIndex>2016-07-30T01:55:13.000Z</maxDateTimeIndex><curveDescription>RawData[0]</curveDescription><typeLogData>long</typeLogData></logCurveInfo><logCurveInfo uid="MWIN"><mnemonic>MWIN</mnemonic><classWitsml>wtMudInAv</classWitsml><unit>kg/m3</unit><mnemAlias>MWIN</mnemAlias><minDateTimeIndex>2016-07-30T01:51:29.000Z</minDateTimeIndex><maxDateTimeIndex>2016-07-30T01:55:13.000Z</maxDateTimeIndex><curveDescription>Mud Weight In</curveDescription><typeLogData>double</typeLogData></logCurveInfo><logCurveInfo uid="BIT_RPM_AVG"><mnemonic>BIT_RPM_AVG</mnemonic><unit>c/s</unit><mnemAlias>BIT_RPM_AVG</mnemAlias><minDateTimeIndex>2016-07-30T01:51:29.000Z</minDateTimeIndex><maxDateTimeIndex>2016-07-30T01:55:13.000Z</maxDateTimeIndex><curveDescription>Bit RPM - Total RPM</curveDescription><typeLogData>double</typeLogData></logCurveInfo><logCurveInfo uid="STRATE6"><mnemonic>STRATE6</mnemonic><classWitsml>spm</classWitsml><unit>Hz</unit><mnemAlias>STRATE6</mnemAlias><minDateTimeIndex>2016-07-30T01:51:29.000Z</minDateTimeIndex><maxDateTimeIndex>2016-07-30T01:55:13.000Z</maxDateTimeIndex><curveDescription>Pump 6 Stroke Rate</curveDescription><typeLogData>double</typeLogData></logCurveInfo><logCurveInfo uid="TOTGAS2"><mnemonic>TOTGAS2</mnemonic><unit>Euc</unit><mnemAlias>TOTGAS2</mnemAlias><minDateTimeIndex>2016-07-30T01:51:29.000Z</minDateTimeIndex><maxDateTimeIndex>2016-07-30T01:55:13.000Z</maxDateTimeIndex><curveDescription>Total Gas 2</curveDescription><typeLogData>double</typeLogData></logCurveInfo><logCurveInfo uid="STRATE4"><mnemonic>STRATE4</mnemonic><classWitsml>spm</classWitsml><unit>Hz</unit><mnemAlias>STRATE4</mnemAlias><minDateTimeIndex>2016-07-30T01:51:29.000Z</minDateTimeIndex><maxDateTimeIndex>2016-07-30T01:55:13.000Z</maxDateTimeIndex><curveDescription>Pump 4 Stroke Rate</curveDescription><typeLogData>double</typeLogData></logCurveInfo><logCurveInfo uid="HKLD_AVG"><mnemonic>HKLD_AVG</mnemonic><unit>N</unit><mnemAlias>HKLD_AVG</mnemAlias><minDateTimeIndex>2016-07-30T01:51:29.000Z</minDateTimeIndex><maxDateTimeIndex>2016-07-30T01:55:13.000Z</maxDateTimeIndex><curveDescription>Hookload</curveDescription><typeLogData>double</typeLogData></logCurveInfo><logCurveInfo uid="TORQUE_AVG"><mnemonic>TORQUE_AVG</mnemonic><unit>N.m</unit><mnemAlias>TORQUE_AVG</mnemAlias><minDateTimeIndex>2016-07-30T01:51:29.000Z</minDateTimeIndex><maxDateTimeIndex>2016-07-30T01:55:13.000Z</maxDateTimeIndex><curveDescription>Surface Torque Average</curveDescription><typeLogData>double</typeLogData></logCurveInfo><logCurveInfo uid="BIT_RPM_MIN"><mnemonic>BIT_RPM_MIN</mnemonic><unit>c/s</unit><mnemAlias>BIT_RPM_MIN</mnemAlias><minDateTimeIndex>2016-07-30T01:51:29.000Z</minDateTimeIndex><maxDateTimeIndex>2016-07-30T01:55:13.000Z</maxDateTimeIndex><curveDescription>Bit RPM - Total RPM</curveDescription><typeLogData>double</typeLogData></logCurveInfo><logCurveInfo uid="OFFBOTTOM_TIME"><mnemonic>OFFBOTTOM_TIME</mnemonic><unit>s</unit><mnemAlias>OFFBOTTOM_TIME</mnemAlias><minDateTimeIndex>2016-07-30T01:51:29.000Z</minDateTimeIndex><maxDateTimeIndex>2016-07-30T01:55:13.000Z</maxDateTimeIndex><curveDescription>Cumulative Off-Bottom Time</curveDescription><typeLogData>double</typeLogData></logCurveInfo><logCurveInfo uid="TORQUE_MIN"><mnemonic>TORQUE_MIN</mnemonic><unit>N.m</unit><mnemAlias>TORQUE_MIN</mnemAlias><minDateTimeIndex>2016-07-30T01:51:29.000Z</minDateTimeIndex><maxDateTimeIndex>2016-07-30T01:55:13.000Z</maxDateTimeIndex><curveDescription>Surface Torque Average</curveDescription><typeLogData>double</typeLogData></logCurveInfo><logCurveInfo uid="I_MSE"><mnemonic>I_MSE</mnemonic><unit>Pa</unit><mnemAlias>I_MSE</mnemAlias><minDateTimeIndex>2016-07-30T01:51:29.000Z</minDateTimeIndex><maxDateTimeIndex>2016-07-30T01:55:13.000Z</maxDateTimeIndex><curveDescription>Interpolated Mechanical Specific Energy</curveDescription><typeLogData>double</typeLogData></logCurveInfo><logCurveInfo uid="LINEWEAR"><mnemonic>LINEWEAR</mnemonic><unit>J</unit><mnemAlias>LINEWEAR</mnemAlias><minDateTimeIndex>2016-07-30T01:51:29.000Z</minDateTimeIndex><maxDateTimeIndex>2016-07-30T01:55:13.000Z</maxDateTimeIndex><curveDescription>Line Wear</curveDescription><typeLogData>double</typeLogData></logCurveInfo><logCurveInfo uid="FLOWOUT_CORIOLIS"><mnemonic>FLOWOUT_CORIOLIS</mnemonic><classWitsml>flowout_Coriolis</classWitsml><unit>m3/s</unit><mnemAlias>FLOWOUT_CORIOLIS</mnemAlias><minDateTimeIndex>2016-07-30T01:51:29.000Z</minDateTimeIndex><maxDateTimeIndex>2016-07-30T01:55:13.000Z</maxDateTimeIndex><curveDescription>Mud flow out from Coriolis</curveDescription><typeLogData>double</typeLogData></logCurveInfo><logCurveInfo uid="GAINLOSSTOT"><mnemonic>GAINLOSSTOT</mnemonic><unit>m3</unit><mnemAlias>GAINLOSSTOT</mnemAlias><minDateTimeIndex>2016-07-30T01:51:29.000Z</minDateTimeIndex><maxDateTimeIndex>2016-07-30T01:55:13.000Z</maxDateTimeIndex><curveDescription>Total Pit Gain/Loss Volume</curveDescription><typeLogData>double</typeLogData></logCurveInfo><logCurveInfo uid="TQ_IN_AMPS_AV"><mnemonic>TQ_IN_AMPS_AV</mnemonic><unit>A</unit><mnemAlias>TQ_IN_AMPS_AV</mnemAlias><minDateTimeIndex>2016-07-30T01:51:29.000Z</minDateTimeIndex><maxDateTimeIndex>2016-07-30T01:55:13.000Z</maxDateTimeIndex><curveDescription>Torque In Amps</curveDescription><typeLogData>double</typeLogData></logCurveInfo><logCurveInfo uid="HKLD_MAX"><mnemonic>HKLD_MAX</mnemonic><unit>N</unit><mnemAlias>HKLD_MAX</mnemAlias><minDateTimeIndex>2016-07-30T01:51:29.000Z</minDateTimeIndex><maxDateTimeIndex>2016-07-30T01:55:13.000Z</maxDateTimeIndex><curveDescription>Hookload</curveDescription><typeLogData>double</typeLogData></logCurveInfo><logCurveInfo uid="TQ_IN_AMPS_MX"><mnemonic>TQ_IN_AMPS_MX</mnemonic><unit>A</unit><mnemAlias>TQ_IN_AMPS_MX</mnemAlias><minDateTimeIndex>2016-07-30T01:51:29.000Z</minDateTimeIndex><maxDateTimeIndex>2016-07-30T01:55:13.000Z</maxDateTimeIndex><curveDescription>Torque In Amps</curveDescription><typeLogData>double</typeLogData></logCurveInfo><logCurveInfo uid="BIT_RPM_MAX"><mnemonic>BIT_RPM_MAX</mnemonic><unit>c/s</unit><mnemAlias>BIT_RPM_MAX</mnemAlias><minDateTimeIndex>2016-07-30T01:51:29.000Z</minDateTimeIndex><maxDateTimeIndex>2016-07-30T01:55:13.000Z</maxDateTimeIndex><curveDescription>Bit RPM - Total RPM</curveDescription><typeLogData>double</typeLogData></logCurveInfo><logCurveInfo uid="DMSE"><mnemonic>DMSE</mnemonic><unit>Pa</unit><mnemAlias>DMSE</mnemAlias><minDateTimeIndex>2016-07-30T01:51:29.000Z</minDateTimeIndex><maxDateTimeIndex>2016-07-30T01:55:13.000Z</maxDateTimeIndex><curveDescription>Delta MSE</curveDescription><typeLogData>double</typeLogData></logCurveInfo><logCurveInfo uid="MTIN"><mnemonic>MTIN</mnemonic><classWitsml>tempMudInAv</classWitsml><unit>K</unit><mnemAlias>MTIN</mnemAlias><minDateTimeIndex>2016-07-30T01:51:29.000Z</minDateTimeIndex><maxDateTimeIndex>2016-07-30T01:55:13.000Z</maxDateTimeIndex><curveDescription>Mud Temperature In</curveDescription><typeLogData>double</typeLogData></logCurveInfo><logCurveInfo uid="MWOUT"><mnemonic>MWOUT</mnemonic><classWitsml>wtMudOutAv</classWitsml><unit>kg/m3</unit><mnemAlias>MWOUT</mnemAlias><minDateTimeIndex>2016-07-30T01:51:29.000Z</minDateTimeIndex><maxDateTimeIndex>2016-07-30T01:55:13.000Z</maxDateTimeIndex><curveDescription>Mud Weight Out</curveDescription><typeLogData>double</typeLogData></logCurveInfo><logCurveInfo uid="PIT_EQMD"><mnemonic>PIT_EQMD</mnemonic><unit>kg/m3</unit><mnemAlias>PIT_EQMD</mnemAlias><minDateTimeIndex>2016-07-30T01:51:29.000Z</minDateTimeIndex><maxDateTimeIndex>2016-07-30T01:55:13.000Z</maxDateTimeIndex><curveDescription>Pressure Integrity Test EQMD</curveDescription><typeLogData>double</typeLogData></logCurveInfo><logCurveInfo uid="TQ_IN_AMPS"><mnemonic>TQ_IN_AMPS</mnemonic><unit>A</unit><mnemAlias>TQ_IN_AMPS</mnemAlias><minDateTimeIndex>2016-07-30T01:51:29.000Z</minDateTimeIndex><maxDateTimeIndex>2016-07-30T01:55:13.000Z</maxDateTimeIndex><curveDescription>Torque In Amps</curveDescription><typeLogData>double</typeLogData></logCurveInfo><logCurveInfo uid="PUMP"><mnemonic>PUMP</mnemonic><classWitsml>presPumpAv</classWitsml><unit>Pa</unit><mnemAlias>PUMP</mnemAlias><minDateTimeIndex>2016-07-30T01:51:29.000Z</minDateTimeIndex><maxDateTimeIndex>2016-07-30T01:55:13.000Z</maxDateTimeIndex><curveDescription>Pump Pressure - Stand Pipe</curveDescription><typeLogData>double</typeLogData></logCurveInfo><logCurveInfo uid="STRATESUM"><mnemonic>STRATESUM</mnemonic><classWitsml>spmTot</classWitsml><unit>Hz</unit><mnemAlias>STRATESUM</mnemAlias><minDateTimeIndex>2016-07-30T01:51:29.000Z</minDateTimeIndex><maxDateTimeIndex>2016-07-30T01:55:13.000Z</maxDateTimeIndex><curveDescription>Pump Total Stroke Rate</curveDescription><typeLogData>double</typeLogData></logCurveInfo><logCurveInfo uid="RUNCIRC"><mnemonic>RUNCIRC</mnemonic><unit>s</unit><mnemAlias>RUNCIRC</mnemAlias><minDateTimeIndex>2016-07-30T01:51:29.000Z</minDateTimeIndex><maxDateTimeIndex>2016-07-30T01:55:13.000Z</maxDateTimeIndex><curveDescription>Run Circulating Hours</curveDescription><typeLogData>double</typeLogData></logCurveInfo><logCurveInfo uid="BLOCKCOMP"><mnemonic>BLOCKCOMP</mnemonic><unit>m</unit><mnemAlias>BLOCKCOMP</mnemAlias><minDateTimeIndex>2016-07-30T01:51:29.000Z</minDateTimeIndex><maxDateTimeIndex>2016-07-30T01:55:13.000Z</maxDateTimeIndex><curveDescription>Block/Topdrive Position Compensated</curveDescription><typeLogData>double</typeLogData></logCurveInfo><logCurveInfo uid="STROKESUM"><mnemonic>STROKESUM</mnemonic><classWitsml>stkTot</classWitsml><unit>unitless</unit><mnemAlias>STROKESUM</mnemAlias><minDateTimeIndex>2016-07-30T01:51:29.000Z</minDateTimeIndex><maxDateTimeIndex>2016-07-30T01:55:13.000Z</maxDateTimeIndex><curveDescription>Pump Total Cumulative Stroke Sum</curveDescription><typeLogData>double</typeLogData></logCurveInfo><logCurveInfo uid="LAG_TIME_RISER"><mnemonic>LAG_TIME_RISER</mnemonic><unit>s</unit><mnemAlias>LAG_TIME_RISER</mnemAlias><minDateTimeIndex>2016-07-30T01:51:29.000Z</minDateTimeIndex><maxDateTimeIndex>2016-07-30T01:55:13.000Z</maxDateTimeIndex><curveDescription>Lag Time Well Head to Surface</curveDescription><typeLogData>double</typeLogData></logCurveInfo><logCurveInfo uid="FRAC_EQMD"><mnemonic>FRAC_EQMD</mnemonic><classWitsml>mffp</classWitsml><unit>kg/m3</unit><mnemAlias>FRAC_EQMD</mnemAlias><minDateTimeIndex>2016-07-30T01:51:29.000Z</minDateTimeIndex><maxDateTimeIndex>2016-07-30T01:55:13.000Z</maxDateTimeIndex><curveDescription>Estimated Fracture Pressure EQMD</curveDescription><typeLogData>double</typeLogData></logCurveInfo><logCurveInfo uid="HKLD_MIN"><mnemonic>HKLD_MIN</mnemonic><unit>N</unit><mnemAlias>HKLD_MIN</mnemAlias><minDateTimeIndex>2016-07-30T01:51:29.000Z</minDateTimeIndex><maxDateTimeIndex>2016-07-30T01:55:13.000Z</maxDateTimeIndex><curveDescription>Hookload</curveDescription><typeLogData>double</typeLogData></logCurveInfo><logCurveInfo uid="TQ_IN_AMPS_MN"><mnemonic>TQ_IN_AMPS_MN</mnemonic><unit>A</unit><mnemAlias>TQ_IN_AMPS_MN</mnemAlias><minDateTimeIndex>2016-07-30T01:51:29.000Z</minDateTimeIndex><maxDateTimeIndex>2016-07-30T01:55:13.000Z</maxDateTimeIndex><curveDescription>Torque In Amps</curveDescription><typeLogData>double</typeLogData></logCurveInfo><logCurveInfo uid="LAG_RSR_STKS"><mnemonic>LAG_RSR_STKS</mnemonic><unit>unitless</unit><mnemAlias>LAG_RSR_STKS</mnemAlias><minDateTimeIndex>2016-07-30T01:51:29.000Z</minDateTimeIndex><maxDateTimeIndex>2016-07-30T01:55:13.000Z</maxDateTimeIndex><curveDescription>Lag Strokes Wellhead to Surface</curveDescription><typeLogData>double</typeLogData></logCurveInfo><logCurveInfo uid="Time"><mnemonic>Time</mnemonic><unit>unitless</unit><mnemAlias>Time</mnemAlias><minDateTimeIndex>2016-07-30T01:51:29.000Z</minDateTimeIndex><maxDateTimeIndex>2016-07-30T01:55:13.000Z</maxDateTimeIndex><curveDescription>The mnemonic of the index curve</curveDescription><typeLogData>date time</typeLogData></logCurveInfo><logCurveInfo uid="STRATE2"><mnemonic>STRATE2</mnemonic><classWitsml>spm</classWitsml><unit>Hz</unit><mnemAlias>STRATE2</mnemAlias><minDateTimeIndex>2016-07-30T01:51:29.000Z</minDateTimeIndex><maxDateTimeIndex>2016-07-30T01:55:13.000Z</maxDateTimeIndex><curveDescription>Pump 2 Stroke Rate</curveDescription><typeLogData>double</typeLogData></logCurveInfo><logCurveInfo uid="CASPR"><mnemonic>CASPR</mnemonic><classWitsml>chkPrAv</classWitsml><unit>Pa</unit><mnemAlias>CASPR</mnemAlias><minDateTimeIndex>2016-07-30T01:51:29.000Z</minDateTimeIndex><maxDateTimeIndex>2016-07-30T01:55:13.000Z</maxDateTimeIndex><curveDescription>Casing Pressure</curveDescription><typeLogData>double</typeLogData></logCurveInfo><logCurveInfo uid="CUMCIRCTIME"><mnemonic>CUMCIRCTIME</mnemonic><unit>s</unit><mnemAlias>CUMCIRCTIME</mnemAlias><minDateTimeIndex>2016-07-30T01:51:29.000Z</minDateTimeIndex><maxDateTimeIndex>2016-07-30T01:55:13.000Z</maxDateTimeIndex><curveDescription>Cumulative Circulating Time</curveDescription><typeLogData>double</typeLogData></logCurveInfo><logCurveInfo uid="STRATE5"><mnemonic>STRATE5</mnemonic><classWitsml>spm</classWitsml><unit>Hz</unit><mnemAlias>STRATE5</mnemAlias><minDateTimeIndex>2016-07-30T01:51:29.000Z</minDateTimeIndex><maxDateTimeIndex>2016-07-30T01:55:13.000Z</maxDateTimeIndex><curveDescription>Pump 5 Stroke Rate</curveDescription><typeLogData>double</typeLogData></logCurveInfo><logCurveInfo uid="ROT_TIME"><mnemonic>ROT_TIME</mnemonic><unit>s</unit><mnemAlias>ROT_TIME</mnemAlias><minDateTimeIndex>2016-07-30T01:51:29.000Z</minDateTimeIndex><maxDateTimeIndex>2016-07-30T01:55:13.000Z</maxDateTimeIndex><curveDescription>Cumulative Rotating Time</curveDescription><typeLogData>double</typeLogData></logCurveInfo><logCurveInfo uid="MRIN"><mnemonic>MRIN</mnemonic><classWitsml>condMudInAv</classWitsml><unit>ohm.m</unit><mnemAlias>MRIN</mnemAlias><minDateTimeIndex>2016-07-30T01:51:29.000Z</minDateTimeIndex><maxDateTimeIndex>2016-07-30T01:55:13.000Z</maxDateTimeIndex><curveDescription>Mud Resistivity In</curveDescription><typeLogData>double</typeLogData></logCurveInfo><logCurveInfo uid="KILL_PRESS"><mnemonic>KILL_PRESS</mnemonic><unit>Pa</unit><mnemAlias>KILL_PRESS</mnemAlias><minDateTimeIndex>2016-07-30T01:51:29.000Z</minDateTimeIndex><maxDateTimeIndex>2016-07-30T01:55:13.000Z</maxDateTimeIndex><curveDescription>Kill Pressure</curveDescription><typeLogData>double</typeLogData></logCurveInfo><logCurveInfo uid="SURF_RPM"><mnemonic>SURF_RPM</mnemonic><classWitsml>rpmAv</classWitsml><unit>c/s</unit><mnemAlias>SURF_RPM</mnemAlias><minDateTimeIndex>2016-07-30T01:51:29.000Z</minDateTimeIndex><maxDateTimeIndex>2016-07-30T01:55:13.000Z</maxDateTimeIndex><curveDescription>Surface RPM</curveDescription><typeLogData>double</typeLogData></logCurveInfo><logCurveInfo uid="TIME_DIST"><mnemonic>TIME_DIST</mnemonic><unit>s/m</unit><mnemAlias>TIME_DIST</mnemAlias><minDateTimeIndex>2016-07-30T01:51:29.000Z</minDateTimeIndex><maxDateTimeIndex>2016-07-30T01:55:13.000Z</maxDateTimeIndex><curveDescription>Time/Distance ROP  - Instantaneous</curveDescription><typeLogData>double</typeLogData></logCurveInfo><logCurveInfo uid="MUDRETDEPTH"><mnemonic>MUDRETDEPTH</mnemonic><unit>m</unit><mnemAlias>MUDRETDEPTH</mnemAlias><minDateTimeIndex>2016-07-30T01:51:29.000Z</minDateTimeIndex><maxDateTimeIndex>2016-07-30T01:55:13.000Z</maxDateTimeIndex><curveDescription>Lagged Mud Returns Depth</curveDescription><typeLogData>double</typeLogData></logCurveInfo><logCurveInfo uid="LAGSTROKES"><mnemonic>LAGSTROKES</mnemonic><classWitsml>stkLag</classWitsml><unit>unitless</unit><mnemAlias>LAGSTROKES</mnemAlias><minDateTimeIndex>2016-07-30T01:51:29.000Z</minDateTimeIndex><maxDateTimeIndex>2016-07-30T01:55:13.000Z</maxDateTimeIndex><curveDescription>Lag Strokes</curveDescription><typeLogData>double</typeLogData></logCurveInfo><logCurveInfo uid="MTOUT"><mnemonic>MTOUT</mnemonic><classWitsml>tempMudOAv</classWitsml><unit>K</unit><mnemAlias>MTOUT</mnemAlias><minDateTimeIndex>2016-07-30T01:51:29.000Z</minDateTimeIndex><maxDateTimeIndex>2016-07-30T01:55:13.000Z</maxDateTimeIndex><curveDescription>Mud Temperature Out</curveDescription><typeLogData>double</typeLogData></logCurveInfo><logCurveInfo uid="BST_STROKESUM"><mnemonic>BST_STROKESUM</mnemonic><unit>unitless</unit><mnemAlias>BST_STROKESUM</mnemAlias><minDateTimeIndex>2016-07-30T01:51:29.000Z</minDateTimeIndex><maxDateTimeIndex>2016-07-30T01:55:13.000Z</maxDateTimeIndex><curveDescription>Booster Strokes Cumulative Total</curveDescription><typeLogData>double</typeLogData></logCurveInfo><logCurveInfo uid="WOB_MIN"><mnemonic>WOB_MIN</mnemonic><unit>N</unit><mnemAlias>WOB_MIN</mnemAlias><minDateTimeIndex>2016-07-30T01:51:29.000Z</minDateTimeIndex><maxDateTimeIndex>2016-07-30T01:55:13.000Z</maxDateTimeIndex><curveDescription>Weight On Bit</curveDescription><typeLogData>double</typeLogData></logCurveInfo><logCurveInfo uid="ROP_AVG"><mnemonic>ROP_AVG</mnemonic><unit>m/s</unit><mnemAlias>ROP_AVG</mnemAlias><minDateTimeIndex>2016-07-30T01:51:29.000Z</minDateTimeIndex><maxDateTimeIndex>2016-07-30T01:55:13.000Z</maxDateTimeIndex><curveDescription>Time Averaged ROP</curveDescription><typeLogData>double</typeLogData></logCurveInfo><logCurveInfo uid="STRATE3"><mnemonic>STRATE3</mnemonic><classWitsml>spm</classWitsml><unit>Hz</unit><mnemAlias>STRATE3</mnemAlias><minDateTimeIndex>2016-07-30T01:51:29.000Z</minDateTimeIndex><maxDateTimeIndex>2016-07-30T01:55:13.000Z</maxDateTimeIndex><curveDescription>Pump 3 Stroke Rate</curveDescription><typeLogData>double</typeLogData></logCurveInfo><logCurveInfo uid="TOTGAS"><mnemonic>TOTGAS</mnemonic><classWitsml>gasAv</classWitsml><unit>Euc</unit><mnemAlias>TOTGAS</mnemAlias><minDateTimeIndex>2016-07-30T01:51:29.000Z</minDateTimeIndex><maxDateTimeIndex>2016-07-30T01:55:13.000Z</maxDateTimeIndex><curveDescription>Total Gas</curveDescription><typeLogData>double</typeLogData></logCurveInfo><logCurveInfo uid="CHOKE_HIGH"><mnemonic>CHOKE_HIGH</mnemonic><unit>Pa</unit><mnemAlias>CHOKE_HIGH</mnemAlias><minDateTimeIndex>2016-07-30T01:51:29.000Z</minDateTimeIndex><maxDateTimeIndex>2016-07-30T01:55:13.000Z</maxDateTimeIndex><curveDescription>Choke Pressure</curveDescription><typeLogData>double</typeLogData></logCurveInfo><logCurveInfo uid="FLOWIN"><mnemonic>FLOWIN</mnemonic><classWitsml>flowInAv</classWitsml><unit>m3/s</unit><mnemAlias>FLOWIN</mnemAlias><minDateTimeIndex>2016-07-30T01:51:29.000Z</minDateTimeIndex><maxDateTimeIndex>2016-07-30T01:55:13.000Z</maxDateTimeIndex><curveDescription>Mud Flow In</curveDescription><typeLogData>double</typeLogData></logCurveInfo><logCurveInfo uid="DWOR"><mnemonic>DWOR</mnemonic><unit>N</unit><mnemAlias>DWOR</mnemAlias><minDateTimeIndex>2016-07-30T01:51:29.000Z</minDateTimeIndex><maxDateTimeIndex>2016-07-30T01:55:13.000Z</maxDateTimeIndex><curveDescription>Delta Weight on Reamer</curveDescription><typeLogData>double</typeLogData></logCurveInfo><logCurveInfo uid="LAG_WELLHD_STKS"><mnemonic>LAG_WELLHD_STKS</mnemonic><unit>unitless</unit><mnemAlias>LAG_WELLHD_STKS</mnemAlias><minDateTimeIndex>2016-07-30T01:51:29.000Z</minDateTimeIndex><maxDateTimeIndex>2016-07-30T01:55:13.000Z</maxDateTimeIndex><curveDescription>Lag Strokes Bit to Wellhead</curveDescription><typeLogData>double</typeLogData></logCurveInfo><logCurveInfo uid="MIN_5FT"><mnemonic>MIN_5FT</mnemonic><unit>s</unit><mnemAlias>MIN_5FT</mnemAlias><minDateTimeIndex>2016-07-30T01:51:29.000Z</minDateTimeIndex><maxDateTimeIndex>2016-07-30T01:55:13.000Z</maxDateTimeIndex><curveDescription>Minutes/last 5 feet</curveDescription><typeLogData>double</typeLogData></logCurveInfo><logCurveInfo uid="BITDEP"><mnemonic>BITDEP</mnemonic><unit>m</unit><mnemAlias>BITDEP</mnemAlias><minDateTimeIndex>2016-07-30T01:51:29.000Z</minDateTimeIndex><maxDateTimeIndex>2016-07-30T01:55:13.000Z</maxDateTimeIndex><curveDescription>Bit Measured Depth</curveDescription><typeLogData>double</typeLogData></logCurveInfo><logCurveInfo uid="POR_EQMD"><mnemonic>POR_EQMD</mnemonic><classWitsml>mfpp</classWitsml><unit>kg/m3</unit><mnemAlias>POR_EQMD</mnemAlias><minDateTimeIndex>2016-07-30T01:51:29.000Z</minDateTimeIndex><maxDateTimeIndex>2016-07-30T01:55:13.000Z</maxDateTimeIndex><curveDescription>Estimated Pore Pressure EQMD</curveDescription><typeLogData>double</typeLogData></logCurveInfo><logCurveInfo uid="STRATE1"><mnemonic>STRATE1</mnemonic><classWitsml>spm</classWitsml><unit>Hz</unit><mnemAlias>STRATE1</mnemAlias><minDateTimeIndex>2016-07-30T01:51:29.000Z</minDateTimeIndex><maxDateTimeIndex>2016-07-30T01:55:13.000Z</maxDateTimeIndex><curveDescription>Pump 1 Stroke Rate</curveDescription><typeLogData>double</typeLogData></logCurveInfo><logCurveInfo uid="PUMP2"><mnemonic>PUMP2</mnemonic><unit>Pa</unit><mnemAlias>PUMP2</mnemAlias><minDateTimeIndex>2016-07-30T01:51:29.000Z</minDateTimeIndex><maxDateTimeIndex>2016-07-30T01:55:13.000Z</maxDateTimeIndex><curveDescription>SARA2 Channel 2 Pump Pressure</curveDescription><typeLogData>double</typeLogData></logCurveInfo><logCurveInfo uid="MROUT"><mnemonic>MROUT</mnemonic><classWitsml>condMudOutAv</classWitsml><unit>ohm.m</unit><mnemAlias>MROUT</mnemAlias><minDateTimeIndex>2016-07-30T01:51:29.000Z</minDateTimeIndex><maxDateTimeIndex>2016-07-30T01:55:13.000Z</maxDateTimeIndex><curveDescription>Mud Resistivity Out</curveDescription><typeLogData>double</typeLogData></logCurveInfo><logCurveInfo uid="WOB_AVG"><mnemonic>WOB_AVG</mnemonic><unit>N</unit><mnemAlias>WOB_AVG</mnemAlias><minDateTimeIndex>2016-07-30T01:51:29.000Z</minDateTimeIndex><maxDateTimeIndex>2016-07-30T01:55:13.000Z</maxDateTimeIndex><curveDescription>Weight On Bit</curveDescription><typeLogData>double</typeLogData></logCurveInfo><logCurveInfo uid="I_BITAGG"><mnemonic>I_BITAGG</mnemonic><unit>unitless</unit><mnemAlias>I_BITAGG</mnemAlias><minDateTimeIndex>2016-07-30T01:51:29.000Z</minDateTimeIndex><maxDateTimeIndex>2016-07-30T01:55:13.000Z</maxDateTimeIndex><curveDescription>Interpolated Bit Aggressiveness</curveDescription><typeLogData>double</typeLogData></logCurveInfo><logCurveInfo uid="LAG_TIME_WELLHD"><mnemonic>LAG_TIME_WELLHD</mnemonic><unit>s</unit><mnemAlias>LAG_TIME_WELLHD</mnemAlias><minDateTimeIndex>2016-07-30T01:51:29.000Z</minDateTimeIndex><maxDateTimeIndex>2016-07-30T01:55:13.000Z</maxDateTimeIndex><curveDescription>Lag Time from Bit to Wellhead</curveDescription><typeLogData>double</typeLogData></logCurveInfo><logCurveInfo uid="Depth"><mnemonic>Depth</mnemonic><unit>m</unit><mnemAlias>Depth</mnemAlias><minDateTimeIndex>2016-07-30T01:51:29.000Z</minDateTimeIndex><maxDateTimeIndex>2016-07-30T01:55:13.000Z</maxDateTimeIndex><curveDescription>The mnemonic of the Hole depth</curveDescription><typeLogData>double</typeLogData></logCurveInfo><logCurveInfo uid="WOB_MAX"><mnemonic>WOB_MAX</mnemonic><unit>N</unit><mnemAlias>WOB_MAX</mnemAlias><minDateTimeIndex>2016-07-30T01:51:29.000Z</minDateTimeIndex><maxDateTimeIndex>2016-07-30T01:55:13.000Z</maxDateTimeIndex><curveDescription>Weight On Bit</curveDescription><typeLogData>double</typeLogData></logCurveInfo><logCurveInfo uid="CHOKE_PRESS"><mnemonic>CHOKE_PRESS</mnemonic><unit>Pa</unit><mnemAlias>CHOKE_PRESS</mnemAlias><minDateTimeIndex>2016-07-30T01:51:29.000Z</minDateTimeIndex><maxDateTimeIndex>2016-07-30T01:55:13.000Z</maxDateTimeIndex><curveDescription>Choke Pressure</curveDescription><typeLogData>double</typeLogData></logCurveInfo><logData><mnemonicList>Time,FLOWOUTPC,FLOWOUT,MOTOR_RPM,PITTOT,MIN_2M,KILL_HIGH,RigActivityCode,TORQUE_MAX,MSE,ONBOTTOM_TIME,RIGHEAVE,EditFlag,MWIN,BIT_RPM_AVG,STRATE6,TOTGAS2,STRATE4,HKLD_AVG,TORQUE_AVG,BIT_RPM_MIN,OFFBOTTOM_TIME,TORQUE_MIN,I_MSE,LINEWEAR,FLOWOUT_CORIOLIS,GAINLOSSTOT,TQ_IN_AMPS_AV,HKLD_MAX,TQ_IN_AMPS_MX,BIT_RPM_MAX,DMSE,MTIN,MWOUT,PIT_EQMD,TQ_IN_AMPS,PUMP,STRATESUM,RUNCIRC,BLOCKCOMP,STROKESUM,LAG_TIME_RISER,FRAC_EQMD,HKLD_MIN,TQ_IN_AMPS_MN,LAG_RSR_STKS,STRATE2,CASPR,CUMCIRCTIME,STRATE5,ROT_TIME,MRIN,KILL_PRESS,SURF_RPM,TIME_DIST,MUDRETDEPTH,LAGSTROKES,MTOUT,BST_STROKESUM,WOB_MIN,ROP_AVG,STRATE3,TOTGAS,CHOKE_HIGH,FLOWIN,DWOR,LAG_WELLHD_STKS,MIN_5FT,BITDEP,POR_EQMD,STRATE1,PUMP2,MROUT,WOB_AVG,I_BITAGG,LAG_TIME_WELLHD,Depth,WOB_MAX,CHOKE_PRESS</mnemonicList><unitList>unitless,Euc,m3/s,c/s,m3,s,Pa,unitless,N.m,Pa,s,unitless,unitless,kg/m3,c/s,Hz,Euc,Hz,N,N.m,c/s,s,N.m,Pa,J,m3/s,m3,A,N,A,c/s,Pa,K,kg/m3,kg/m3,A,Pa,Hz,s,m,unitless,s,kg/m3,N,A,unitless,Hz,Pa,s,Hz,s,ohm.m,Pa,c/s,s/m,m,unitless,K,unitless,N,m/s,Hz,Euc,Pa,m3/s,N,unitless,s,m,kg/m3,Hz,Pa,ohm.m,N,unitless,s,m,N,Pa</unitList><data>2016-07-30T01:51:29.000Z,0,4.5646534E-05,0,540.15161,0,-41805.472,14,7.501377,0,0,-0.077077746,0,1030,0,0,0,0,642729.5,7.501377,0,40387,7.501377,0,999839730,0,-19.150249,0,642729.5,0,0,0,0,1030,0,0,146759,0,139757,10.75167,918.70457,25115.231,0,642729.5,0,418.58718,0,0,2429.42,0,8041,0,0,0,0,0,580.75747,0,0,97804.359,0,0,0,-101348.4,0,0,162.17029,0,0,1030,0,145652,0,97804.359,0,9730.2174,1083,97804.359,-1665.58</data><data>2016-07-30T01:51:32.000Z,0,4.570197E-05,0,540.35152,0,-48351.219,14,7.501377,0,0,-0.084711115,0,1030,0,0,0,0,644011.5,7.501377,0,40390,7.501377,0,999839730,0,-18.950333,0,646575.5,0,0,0,0,1030,0,0,145303.79,0,139760,10.75167,918.70457,25115.231,0,642729.5,0,418.58718,0,0,2429.42,0,8041,0,0,0,0,0,580.75747,0,0,97804.359,0,0,0,-103276.95,0,0,162.17029,0,0,1030,0,142929,0,97804.359,0,9730.2174,1083,97804.359,3269.54</data><data>2016-07-30T01:51:34.000Z,0,4.5600222E-05,0,540.37084,0,-38118.789,14,7.501377,0,0,-0.079905845,0,1030,0,0,0,0,645842.93,7.501377,0,40392,7.501377,0,999839730,0,-18.931021,0,646575.5,0,0,0,0,1030,0,0,146140.04,0,139762,10.75167,918.70457,25115.231,0,646575.5,0,418.58718,0,0,2429.42,0,8041,0,0,0,0,0,580.75747,0,0,97804.359,0,0,0,-101989.3,0,0,162.17029,0,0,1030,0,150131,0,97804.359,0,9730.2174,1083,97804.359,1013.83</data><data>2016-07-30T01:51:37.000Z,0,4.5745233E-05,0,540.40516,0,-45649.718,14,7.501377,0,0,-0.078628461,0,1030,0,0,0,0,646575.5,7.501377,0,40395,7.501377,0,999839730,0,-18.8967,0,646575.5,0,0,0,0,1030,0,0,146617.8,0,139765,10.75167,918.70457,25115.231,0,646575.5,0,418.58718,0,0,2429.42,0,8041,0,0,0,0,0,580.75747,0,0,93958.359,0,0,0,-101478.86,0,0,162.17029,0,0,1030,0,146121,0,96522.359,0,9730.2174,1083,97804.359,4385.06</data><data>2016-07-30T01:51:40.000Z,0,4.5638431E-05,0,540.30947,0,-41921.544,14,7.501377,0,0,-0.081616143,0,1030,0,0,0,0,646575.5,7.501377,0,40398,7.501377,0,999839730,0,-18.992389,0,646575.5,0,0,0,0,1030,0,0,144660.83,0,139768,10.75167,918.70457,25115.231,0,646575.5,0,418.58718,0,0,2429.42,0,8041,0,0,0,0,0,580.75747,0,0,93958.359,0,0,0,-102394.08,0,0,162.17029,0,0,1030,0,146359,0,93958.359,0,9730.2174,1083,93958.359,1805.79</data><data>2016-07-30T01:51:43.000Z,0,4.5650372E-05,0,540.22865,0,-42744.321,14,7.501377,0,0,-0.079235931,0,1030,0,0,0,0,645293.5,7.501377,0,40401,7.501377,0,999839730,0,-19.073211,0,646575.5,0,0,0,0,1030,0,0,141561.21,0,139771,10.75167,918.70457,25115.231,0,642729.5,0,418.58718,0,0,2429.42,0,8041,0,0,0,0,0,580.75747,0,0,93958.359,0,0,0,-105142.32,0,0,162.17029,0,0,1030,0,149666,0,93958.359,0,9730.2174,1083,93958.359,-7428.1</data><data>2016-07-30T01:51:46.000Z,0,4.5683174E-05,0,540.49184,0,-42727.886,14,7.501377,0,0,-0.075383484,0,1030,0,0,0,0,642729.5,7.501377,0,40404,7.501377,0,999839730,0,-18.810021,0,642729.5,0,0,0,0,1030,0,0,146692.51,0,139774,10.75167,918.70457,25115.231,0,642729.5,0,418.58718,0,0,2429.42,0,8041,0,0,0,0,0,580.75747,0,0,93958.359,0,0,0,-98706.48,0,0,162.17029,0,0,1030,0,151204,0,93958.359,0,9730.2174,1083,93958.359,6739.37</data><data>2016-07-30T01:51:48.000Z,0,4.5638887E-05,0,540.32038,0,-39502.886,14,7.501377,0,0,-0.076488831,0,1030,0,0,0,0,642729.5,7.501377,0,40406,7.501377,0,999839730,0,-18.981477,0,642729.5,0,0,0,0,1030,0,0,146536.82,0,139776,10.75167,918.70457,25115.231,0,642729.5,0,418.58718,0,0,2429.42,0,8041,0,0,0,0,0,580.75747,0,0,93958.359,0,0,0,-97697.636,0,0,162.17029,0,0,1030,0,154862,0,93958.359,0,9730.2174,1083,97804.359,687.188</data><data>2016-07-30T01:51:51.000Z,0,4.5625595E-05,0,540.35805,0,-38218.536,14,7.501377,0,0,-0.078717868,0,1030,0,0,0,0,642729.5,7.501377,0,40409,7.501377,0,999839730,0,-18.943807,0,642729.5,0,0,0,0,1030,0,0,147711.78,0,139779,10.75167,918.70457,25115.231,0,642729.5,0,418.58718,0,0,2429.42,0,8041,0,0,0,0,0,580.75747,0,0,97804.359,0,0,0,-101365.35,0,0,162.17029,0,0,1030,0,144940,0,97804.359,0,9730.2174,1083,97804.359,-3583.85</data><data>2016-07-30T01:51:54.000Z,0,4.5600993E-05,0,540.32016,0,-39130.164,14,7.501377,0,0,-0.079427163,0,1030,0,0,0,0,642729.5,7.501377,0,40412,7.501377,0,999839730,0,-18.981699,0,642729.5,0,0,0,0,1030,0,0,146445.07,0,139782,10.75167,918.70457,25115.231,0,642729.5,0,418.58718,0,0,2429.42,0,8041,0,0,0,0,0,580.75747,0,0,97804.359,0,0,0,-100470.67,0,0,162.17029,0,0,1030,0,144940,0,97804.359,0,9730.2174,1083,97804.359,2027.67</data><data>2016-07-30T01:51:57.000Z,0,4.5710035E-05,0,540.22786,0,-39030.527,14,7.501377,0,0,-0.07960697,0,1030,0,0,0,0,642729.5,7.501377,0,40415,7.501377,0,999839730,0,-19.073993,0,642729.5,0,0,0,0,1030,0,0,149110.11,0,139785,10.75167,918.70457,25115.231,0,642729.5,0,418.58718,0,0,2429.42,0,8041,0,0,0,0,0,580.75747,0,0,97804.359,0,0,0,-99537.474,0,0,162.17029,0,0,1030,0,148724,0,97804.359,0,9730.2174,1083,97804.359,9.24468</data><data>2016-07-30T01:52:00.000Z,0,4.5754835E-05,0,540.1873,0,-42736.103,14,7.501377,0,0,-0.074917575,0,1030,0,0,0,0,644011.5,7.501377,0,40418,7.501377,0,999839730,0,-19.114556,0,646575.5,0,0,0,0,1030,0,0,149051.16,0,139788,10.75167,918.70457,25115.231,0,642729.5,0,418.58718,0,0,2429.42,0,8041,0,0,0,0,0,580.75747,0,0,97804.359,0,0,0,-103423.32,0,0,162.17029,0,0,1030,0,152372,0,97804.359,0,9730.2174,1083,97804.359,3707.12</data><data>2016-07-30T01:52:02.000Z,0,4.5709012E-05,0,540.41585,0,-45473.556,14,7.501377,0,0,-0.074353637,0,1030,0,0,0,0,645842.93,7.501377,0,40420,7.501377,0,999839730,0,-18.88601,0,646575.5,0,0,0,0,1030,0,0,145115.43,0,139790,10.75167,918.70457,25115.231,0,646575.5,0,418.58718,0,0,2429.42,0,8041,0,0,0,0,0,580.75747,0,0,97804.359,0,0,0,-104915.68,0,0,162.17029,0,0,1030,0,147655,0,97804.359,0,9730.2174,1083,97804.359,1805.79</data><data>2016-07-30T01:52:05.000Z,0,4.5690712E-05,0,540.0592,0,-42819.819,14,7.501377,0,0,-0.081260502,0,1030,0,0,0,0,644011.5,7.501377,0,40423,7.501377,0,999839730,0,-19.242654,0,646575.5,0,0,0,0,1030,0,0,145406.6,0,139793,10.75167,918.70457,25115.231,0,642729.5,0,418.58718,0,0,2429.42,0,8041,0,0,0,0,0,580.75747,0,0,97804.359,0,0,0,-101409.01,0,0,162.17029,0,0,1030,0,152973,0,97804.359,0,9730.2174,1083,97804.359,2027.67</data><data>2016-07-30T01:52:08.000Z,0,4.5729435E-05,0,540.42683,0,-41823.448,14,7.501377,0,0,-0.082830091,0,1030,0,0,0,0,642729.5,7.501377,0,40426,7.501377,0,999839730,0,-18.875025,0,642729.5,0,0,0,0,1030,0,0,141097.16,0,139796,10.75167,918.70457,25115.231,0,642729.5,0,418.58718,0,0,2429.42,0,8041,0,0,0,0,0,580.75747,0,0,93958.359,0,0,0,-101403.36,0,0,162.17029,0,0,1030,0,143164,0,95240.359,0,9730.2174,1083,97804.359,123.262</data><data>2016-07-30T01:52:11.000Z,0,4.5663013E-05,0,540.05409,0,-38167.177,14,7.501377,0,0,-0.076286495,0,1030,0,0,0,0,642729.5,7.501377,0,40429,7.501377,0,999839730,0,-19.247763,0,642729.5,0,0,0,0,1030,0,0,142896.47,0,139799,10.75167,918.70457,25115.231,0,642729.5,0,418.58718,0,0,2429.42,0,8041,0,0,0,0,0,580.75747,0,0,93958.359,0,0,0,-93117.043,0,0,162.17029,0,0,1030,0,146713,0,93958.359,0,9730.2174,1083,93958.359,6397.32</data><data>2016-07-30T01:52:14.000Z,0,4.5603934E-05,0,540.43262,0,-38205.183,14,7.501377,0,0,-0.075360636,0,1030,0,0,0,0,646575.5,7.501377,0,40432,7.501377,0,999839730,0,-18.869241,0,646575.5,0,0,0,0,1030,0,0,146568.45,0,139802,10.75167,918.70457,25115.231,0,642729.5,0,418.58718,0,0,2429.42,0,8041,0,0,0,0,0,580.75747,0,0,93958.359,0,0,0,-101377.17,0,0,162.17029,0,0,1030,0,148126,0,96522.359,0,9730.2174,1083,97804.359,6511.34</data><data>2016-07-30T01:52:16.000Z,0,4.5637723E-05,0,540.20468,0,-40158.121,14,7.501377,0,0,-0.078653615,0,1030,0,0,0,0,643828.36,7.501377,0,40434,7.501377,0,999839730,0,-19.097174,0,642729.5,0,0,0,0,1030,0,0,146755.48,0,139804,10.75167,918.70457,25115.231,0,642729.5,0,418.58718,0,0,2429.42,0,8041,0,0,0,0,0,580.75747,0,0,97804.359,0,0,0,-96371.831,0,0,162.17029,0,0,1030,0,145652,0,97438.073,0,9730.2174,1083,97804.359,2144.77</data><data>2016-07-30T01:52:19.000Z,0,4.5787754E-05,0,540.30198,0,-41872.239,14,7.501377,0,0,-0.075062613,0,1030,0,0,0,0,642729.5,7.501377,0,40437,7.501377,0,999839730,0,-18.999878,0,642729.5,0,0,0,0,1030,0,0,147779.64,0,139807,10.75167,918.70457,25115.231,0,642729.5,0,418.58718,0,0,2429.42,0,8041,0,0,0,0,0,580.75747,0,0,93958.359,0,0,0,-99610.918,0,0,162.17029,0,0,1030,0,141986,0,96522.359,0,9730.2174,1083,97804.359,3488.33</data><data>2016-07-30T01:52:22.000Z,0,4.5806318E-05,0,540.4331,0,-43785.374,14,7.501377,0,0,-0.078471502,0,1030,0,0,0,0,644011.5,7.501377,0,40440,7.501377,0,999839730,0,-18.868761,0,646575.5,0,0,0,0,1030,0,0,148288.25,0,139810,10.75167,918.70457,25115.231,0,642729.5,0,418.58718,0,0,2429.42,0,8041,0,0,0,0,0,580.75747,0,0,93958.359,0,0,0,-104195.77,0,0,162.17029,0,0,1030,0,139257,0,93958.359,0,9730.2174,1083,93958.359,-3694.79</data><data>2016-07-30T01:52:25.000Z,0,4.5666773E-05,0,540.36109,0,-43893.743,14,7.501377,0,0,-0.0786677,0,1030,0,0,0,0,645293.5,7.501377,0,40443,7.501377,0,999839730,0,-18.94077,0,646575.5,0,0,0,0,1030,0,0,145044.68,0,139813,10.75167,918.70457,25115.231,0,642729.5,0,418.58718,0,0,2429.42,0,8041,0,0,0,0,0,580.75747,0,0,93958.359,0,0,0,-96821.592,0,0,162.17029,0,0,1030,0,141387,0,95240.359,0,9730.2174,1083,97804.359,-4468.26</data><data>2016-07-30T01:52:28.000Z,0,4.5730838E-05,0,540.3618,0,-41867.617,14,7.501377,0,0,-0.080384811,0,1030,0,0,0,0,644011.5,7.501377,0,40446,7.501377,0,999839730,0,-18.940053,0,646575.5,0,0,0,0,1030,0,0,145305.84,0,139816,10.75167,918.70457,25115.231,0,642729.5,0,418.58718,0,0,2429.42,0,8041,0,0,0,0,0,580.75747,0,0,97804.359,0,0,0,-103288.25,0,0,162.17029,0,0,1030,0,145535,0,97804.359,0,9730.2174,1083,97804.359,7642.27</data><data>2016-07-30T01:52:30.000Z,0,4.574233E-05,0,540.37979,0,-43182.783,14,7.501377,0,0,-0.080372748,0,1030,0,0,0,0,645842.93,7.501377,0,40448,7.501377,0,999839730,0,-18.922067,0,646575.5,0,0,0,0,1030,0,0,144361.14,0,139818,10.75167,918.70457,25115.231,0,646575.5,0,418.58718,0,0,2429.42,0,8041,0,0,0,0,0,580.75747,0,0,97804.359,0,0,0,-99988.959,0,0,162.17029,0,0,1030,0,149545,0,97804.359,0,9730.2174,1083,97804.359,9087.52</data><data>2016-07-30T01:52:33.000Z,0,4.5607694E-05,0,540.4736,0,-35320.329,14,7.501377,0,0,-0.078942378,0,1030,0,0,0,0,644011.5,7.501377,0,40451,7.501377,0,999839730,0,-18.828253,0,646575.5,0,0,0,0,1030,0,0,147911.25,0,139821,10.75167,918.70457,25115.231,0,642729.5,0,418.58718,0,0,2429.42,0,8041,0,0,0,0,0,580.75747,0,0,97804.359,0,0,0,-107809.92,0,0,162.17029,0,0,1030,0,137484,0,97804.359,0,9730.2174,1083,97804.359,1805.79</data><data>2016-07-30T01:52:36.000Z,0,4.5677875E-05,0,540.65591,0,-36352.138,14,7.501377,0,0,-0.078945359,0,1030,0,0,0,0,645293.5,7.501377,0,40454,7.501377,0,999839730,0,-18.645946,0,646575.5,0,0,0,0,1030,0,0,142815.59,0,139824,10.75167,918.70457,25115.231,0,642729.5,0,418.58718,0,0,2429.42,0,8041,0,0,0,0,0,580.75747,0,0,97804.359,0,0,0,-106087.33,0,0,162.17029,0,0,1030,0,150604,0,97804.359,0,9730.2174,1083,97804.359,3593.1</data><data>2016-07-30T01:52:39.000Z,0,4.5673454E-05,0,540.22845,0,-34504.229,14,7.501377,0,0,-0.078688065,0,1030,0,0,0,0,645293.5,7.501377,0,40457,7.501377,0,999839730,0,-19.073409,0,646575.5,0,0,0,0,1030,0,0,144717.72,0,139827,10.75167,918.70457,25115.231,0,642729.5,0,418.58718,0,0,2429.42,0,8041,0,0,0,0,0,580.75747,0,0,97804.359,0,0,0,-100430.1,0,0,162.17029,0,0,1030,0,151556,0,97804.359,0,9730.2174,1083,97804.359,-107.855</data><data>2016-07-30T01:52:42.000Z,0,4.5801935E-05,0,540.10315,0,-39961.672,14,7.501377,0,0,-0.080298881,0,1030,0,0,0,0,642729.5,7.501377,0,40460,7.501377,0,999839730,0,-19.198706,0,642729.5,0,0,0,0,1030,0,0,146118.79,0,139830,10.75167,918.70457,25115.231,0,642729.5,0,418.58718,0,0,2429.42,0,8041,0,0,0,0,0,580.75747,0,0,93958.359,0,0,0,-97741.438,0,0,162.17029,0,0,1030,0,146952,0,97804.359,0,9730.2174,1083,97804.359,2816.55</data><data>2016-07-30T01:52:44.000Z,0,4.5782512E-05,0,540.68969,0,-36664.953,14,7.501377,0,0,-0.083068723,0,1030,0,0,0,0,642729.5,7.501377,0,40462,7.501377,0,999839730,0,-18.61217,0,642729.5,0,0,0,0,1030,0,0,145829.43,0,139832,10.75167,918.70457,25115.231,0,642729.5,0,418.58718,0,0,2429.42,0,8041,0,0,0,0,0,580.75747,0,0,93958.359,0,0,0,-103373.72,0,0,162.17029,0,0,1030,0,141387,0,95057.216,0,9730.2174,1083,93958.359,4724.03</data><data>2016-07-30T01:52:47.000Z,0,4.5611434E-05,0,540.08474,0,-39081.373,14,7.501377,0,0,-0.079878668,0,1030,0,0,0,0,646575.5,7.501377,0,40465,7.501377,0,999839730,0,-19.217117,0,646575.5,0,0,0,0,1030,0,0,144785.58,0,139835,10.75167,918.70457,25115.231,0,646575.5,0,418.58718,0,0,2429.42,0,8041,0,0,0,0,0,580.75747,0,0,93958.359,0,0,0,-101429.04,0,0,162.17029,0,0,1030,0,143045,0,93958.359,0,9730.2174,1083,93958.359,5623.85</data><data>2016-07-30T01:52:50.000Z,0,4.5648618E-05,0,540.36721,0,-40937.499,14,7.501377,0,0,-0.080859164,0,1030,0,0,0,0,649139.63,7.501377,0,40468,7.501377,0,999839730,0,-18.934648,0,650421.7,0,0,0,0,1030,0,0,145995.41,0,139838,10.75167,918.70457,25115.231,0,646575.5,0,418.58718,0,0,2429.42,0,8041,0,0,0,0,0,580.75747,0,0,93958.359,0,0,0,-98649.985,0,0,162.17029,0,0,1030,0,144940,0,96522.359,0,9730.2174,1083,97804.359,7189.28</data><data>2016-07-30T01:52:53.000Z,0,4.5657968E-05,0,540.04587,0,-42749.97,14,7.501377,0,0,-0.077418486,0,1030,0,0,0,0,647857.57,7.501377,0,40471,7.501377,0,999839730,0,-19.255989,0,650421.7,0,0,0,0,1030,0,0,142895.1,0,139841,10.75167,918.70457,25115.231,0,646575.5,0,418.58718,0,0,2429.42,0,8041,0,0,0,0,0,580.75747,0,0,97804.359,0,0,0,-104269.72,0,0,162.17029,0,0,1030,0,148004,0,97804.359,0,9730.2174,1083,97804.359,5740.95</data><data>2016-07-30T01:52:56.000Z,0,4.5800688E-05,0,540.35581,0,-38216.995,14,7.501377,0,0,-0.075900555,0,1030,0,0,0,0,649139.63,7.501377,0,40474,7.501377,0,999839730,0,-18.946051,0,650421.7,0,0,0,0,1030,0,0,147134.63,0,139844,10.75167,918.70457,25115.231,0,646575.5,0,418.58718,0,0,2429.42,0,8041,0,0,0,0,0,580.75747,0,0,90112.159,0,0,0,-100565.69,0,0,162.17029,0,0,1030,0,147542,0,92676.226,0,9730.2174,1083,97804.359,-4583.82</data><data>2016-07-30T01:52:58.000Z,0,4.5676428E-05,0,540.20375,0,-36160.971,14,7.501377,0,0,-0.073294448,0,1030,0,0,0,0,650055.4,7.501377,0,40476,7.501377,0,999839730,0,-19.098108,0,650421.7,0,0,0,0,1030,0,0,143540.41,0,139846,10.75167,918.70457,25115.231,0,646575.5,0,418.58718,0,0,2429.42,0,8041,0,0,0,0,0,580.75747,0,0,90112.159,0,0,0,-104143.23,0,0,162.17029,0,0,1030,0,139374,0,90844.749,0,9730.2174,1083,90112.159,3488.33</data><data>2016-07-30T01:53:01.000Z,0,4.5654735E-05,0,540.5113,0,-39147.113,14,7.501377,0,0,-0.077733397,0,1030,0,0,0,0,646575.5,7.501377,0,40480,7.501377,0,999839730,0,-18.790556,0,646575.5,0,0,0,0,1030,0,0,144601.2,0,139850,10.75167,918.70457,25115.231,0,646575.5,0,418.58718,0,0,2429.42,0,8041,0,0,0,0,0,580.75747,0,0,90112.159,0,0,0,-101431.09,0,0,162.17029,0,0,1030,0,149545,0,90112.159,0,9730.2174,1083,90112.159,7420.4</data><data>2016-07-30T01:53:04.000Z,0,4.5746265E-05,0,540.29618,0,-39098.835,14,7.501377,0,0,-0.079858303,0,1030,0,0,0,0,642729.5,7.501377,0,40483,7.501377,0,999839730,0,-19.005675,0,646575.5,0,0,0,0,1030,0,0,149735.93,0,139853,10.75167,918.70457,25115.231,0,642729.5,0,418.58718,0,0,2429.42,0,8041,0,0,0,0,0,580.75747,0,0,90112.159,0,0,0,-104210.15,0,0,162.17029,0,0,1030,0,150491,0,90112.159,0,9730.2174,1083,90112.159,-1687.15</data><data>2016-07-30T01:53:07.000Z,0,4.5764107E-05,0,540.56164,0,-39024.364,14,7.501377,0,0,-0.078504284,0,1030,0,0,0,0,645293.5,7.501377,0,40486,7.501377,0,999839730,0,-18.740219,0,646575.5,0,0,0,0,1030,0,0,146760.37,0,139856,10.75167,918.70457,25115.231,0,642729.5,0,418.58718,0,0,2429.42,0,8041,0,0,0,0,0,580.75747,0,0,90112.159,0,0,0,-102454.68,0,0,162.17029,0,0,1030,0,148017,0,92676.226,0,9730.2174,1083,97804.359,1577.76</data><data>2016-07-30T01:53:10.000Z,0,4.5668818E-05,0,540.27064,0,-43741.205,14,7.501377,0,0,-0.077775617,0,1030,0,0,0,0,646575.5,7.501377,0,40488,7.501377,0,999839730,0,-19.031216,0,646575.5,0,0,0,0,1030,0,0,146051.62,0,139858,10.75167,918.70457,25115.231,0,646575.5,0,418.58718,0,0,2429.42,0,8041,0,0,0,0,0,580.75747,0,0,97804.359,0,0,0,-100504.57,0,0,162.17029,0,0,1030,0,143045,0,97804.359,0,9730.2174,1083,97804.359,1691.78</data><data>2016-07-30T01:53:12.000Z,0,4.5665193E-05,0,540.68403,0,-46747.377,14,7.501377,0,0,-0.078870498,0,1030,0,0,0,0,646575.5,7.501377,0,40490,7.501377,0,999839730,0,-18.617826,0,646575.5,0,0,0,0,1030,0,0,145807.3,0,139860,10.75167,918.70457,25115.231,0,646575.5,0,418.58718,0,0,2429.42,0,8041,0,0,0,0,0,580.75747,0,0,93958.359,0,0,0,-103161.68,0,0,162.17029,0,0,1030,0,153333,0,97804.359,0,9730.2174,1083,97804.359,-4691.68</data><data>2016-07-30T01:53:15.000Z,0,4.5668156E-05,0,540.1393,0,-41829.097,14,7.501377,0,0,-0.078225633,0,1030,0,0,0,0,646575.5,7.501377,0,40493,7.501377,0,999839730,0,-19.162555,0,646575.5,0,0,0,0,1030,0,0,146232.58,0,139863,10.75167,918.70457,25115.231,0,646575.5,0,418.58718,0,0,2429.42,0,8041,0,0,0,0,0,580.75747,0,0,93958.359,0,0,0,-97658.749,0,0,162.17029,0,0,1030,0,148846,0,93958.359,0,9730.2174,1083,93958.359,-899.816</data><data>2016-07-30T01:53:18.000Z,0,4.5584631E-05,0,540.29942,0,-43674.438,14,7.501377,0,0,-0.0790899,0,1030,0,0,0,0,644011.5,7.501377,0,40496,7.501377,0,999839730,0,-19.002437,0,646575.5,0,0,0,0,1030,0,0,146636.31,0,139866,10.75167,918.70457,25115.231,0,642729.5,0,418.58718,0,0,2429.42,0,8041,0,0,0,0,0,580.75747,0,0,93958.359,0,0,0,-101487.07,0,0,162.17029,0,0,1030,0,148004,0,93958.359,0,9730.2174,1083,93958.359,-3023.01</data><data>2016-07-30T01:53:21.000Z,0,4.5580794E-05,0,540.6282,0,-42046.861,14,7.501377,0,0,-0.077355901,0,1030,0,0,0,0,644011.5,7.501377,0,40499,7.501377,0,999839730,0,-18.673659,0,646575.5,0,0,0,0,1030,0,0,144538.13,0,139869,10.75167,918.70457,25115.231,0,642729.5,0,418.58718,0,0,2429.42,0,8041,0,0,0,0,0,580.75747,0,0,93958.359,0,0,0,-102349.4,0,0,162.17029,0,0,1030,0,141387,0,93958.359,0,9730.2174,1083,93958.359,4511.4</data><data>2016-07-30T01:53:24.000Z,0,4.5695017E-05,0,540.19597,0,-47506.358,14,7.501377,0,0,-0.0799492,0,1030,0,0,0,0,645293.5,7.501377,0,40502,7.501377,0,999839730,0,-19.105886,0,646575.5,0,0,0,0,1030,0,0,146102.34,0,139872,10.75167,918.70457,25115.231,0,642729.5,0,418.58718,0,0,2429.42,0,8041,0,0,0,0,0,580.75747,0,0,93958.359,0,0,0,-105247.6,0,0,162.17029,0,0,1030,0,145173,0,93958.359,0,9730.2174,1083,97804.359,4286.45</data><data>2016-07-30T01:53:26.000Z,0,4.574852E-05,0,540.67177,0,-39860.054,14,7.501377,0,0,-0.080255206,0,1030,0,0,0,0,643462.07,7.501377,0,40504,7.501377,0,999839730,0,-18.630085,0,642729.5,0,0,0,0,1030,0,0,149021.64,0,139874,10.75167,918.70457,25115.231,0,642729.5,0,418.58718,0,0,2429.42,0,8041,0,0,0,0,0,580.75747,0,0,97804.359,0,0,0,-104580.67,0,0,162.17029,0,0,1030,0,146952,0,96705.502,0,9730.2174,1083,97804.359,-3805.73</data><data>2016-07-30T01:53:29.000Z,0,4.5720553E-05,0,540.30821,0,-39057.748,14,7.501377,0,0,-0.075823069,0,1030,0,0,0,0,645293.5,7.501377,0,40507,7.501377,0,999839730,0,-18.993645,0,646575.5,0,0,0,0,1030,0,0,146233.26,0,139877,10.75167,918.70457,25115.231,0,642729.5,0,418.58718,0,0,2429.42,0,8041,0,0,0,0,0,580.75747,0,0,97804.359,0,0,0,-108744.66,0,0,162.17029,0,0,1030,0,144940,0,97804.359,0,9730.2174,1083,97804.359,5740.95</data><data>2016-07-30T01:53:32.000Z,0,4.5752595E-05,0,540.54746,0,-42734.562,14,7.501377,0,0,-0.082714856,0,1030,0,0,0,0,646575.5,7.501377,0,40510,7.501377,0,999839730,0,-18.754399,0,646575.5,0,0,0,0,1030,0,0,144329.76,0,139880,10.75167,918.70457,25115.231,0,646575.5,0,418.58718,0,0,2429.42,0,8041,0,0,0,0,0,580.75747,0,0,97804.359,0,0,0,-101464.48,0,0,162.17029,0,0,1030,0,147423,0,97804.359,0,9730.2174,1083,97804.359,2816.55</data><data>2016-07-30T01:53:35.000Z,0,4.5651618E-05,0,540.02547,0,-38222.645,14,7.501377,0,0,-0.077120463,0,1030,0,0,0,0,642729.5,7.501377,0,40513,7.501377,0,999839730,0,-19.276388,0,646575.5,0,0,0,0,1030,0,0,142473.55,0,139883,10.75167,918.70457,25115.231,0,642729.5,0,418.58718,0,0,2429.42,0,8041,0,0,0,0,0,580.75747,0,0,97804.359,0,0,0,-99588.833,0,0,162.17029,0,0,1030,0,146121,0,97804.359,0,9730.2174,1083,97804.359,-2226.43</data><data>2016-07-30T01:53:38.000Z,0,4.5603818E-05,0,540.50611,0,-41925.653,14,7.501377,0,0,-0.076417128,0,1030,0,0,0,0,641447.47,7.501377,0,40516,7.501377,0,999839730,0,-18.795746,0,642729.5,0,0,0,0,1030,0,0,143407.82,0,139886,10.75167,918.70457,25115.231,0,638883.4,0,418.58718,0,0,2429.42,0,8041,0,0,0,0,0,580.75747,0,0,93958.359,0,0,0,-96832.378,0,0,162.17029,0,0,1030,0,139981,0,95240.359,0,9730.2174,1083,97804.359,-1887.46</data><data>2016-07-30T01:53:40.000Z,0,4.5685795E-05,0,540.01549,0,-39278.079,14,7.501377,0,0,-0.074228077,0,1030,0,0,0,0,639615.99,7.501377,0,40518,7.501377,0,999839730,0,-19.286365,0,638883.4,0,0,0,0,1030,0,0,148312.73,0,139888,10.75167,918.70457,25115.231,0,638883.4,0,418.58718,0,0,2429.42,0,8041,0,0,0,0,0,580.75747,0,0,93958.359,0,0,0,-102073.96,0,0,162.17029,0,0,1030,0,147893,0,94324.645,0,9730.2174,1083,93958.359,-6499.01</data><data>2016-07-30T01:53:43.000Z,0,4.5654053E-05,0,540.8507,0,-46450.41,14,7.501377,0,0,-0.078621507,0,1030,0,0,0,0,646575.5,7.501377,0,40521,7.501377,0,999839730,0,-18.451158,0,646575.5,0,0,0,0,1030,0,0,144904.85,0,139891,10.75167,918.70457,25115.231,0,638883.4,0,418.58718,0,0,2429.42,0,8041,0,0,0,0,0,580.75747,0,0,93958.359,0,0,0,-104185.49,0,0,162.17029,0,0,1030,0,146830,0,96522.392,0,9730.2174,1083,101650.46,5623.85</data><data>2016-07-30T01:53:46.000Z,0,4.5731111E-05,0,540.05063,0,-39042.34,14,7.501377,0,0,-0.079218547,0,1030,0,0,0,0,646575.5,7.501377,0,40524,7.501377,0,999839730,0,-19.251223,0,646575.5,0,0,0,0,1030,0,0,148582.99,0,139894,10.75167,918.70457,25115.231,0,646575.5,0,418.58718,0,0,2429.42,0,8041,0,0,0,0,0,580.75747,0,0,93958.359,0,0,0,-103294.41,0,0,162.17029,0,0,1030,0,150604,0,101650.46,0,9730.2174,1083,101650.46,-107.855</data><data>2016-07-30T01:53:49.000Z,0,4.5630055E-05,0,540.763,0,-47454.485,14,7.501377,0,0,-0.07862548,0,1030,0,0,0,0,646575.5,7.501377,0,40527,7.501377,0,999839730,0,-18.538856,0,646575.5,0,0,0,0,1030,0,0,147951.69,0,139897,10.75167,918.70457,25115.231,0,646575.5,0,418.58718,0,0,2429.42,0,8041,0,0,0,0,0,580.75747,0,0,93958.359,0,0,0,-102429,0,0,162.17029,0,0,1030,0,146952,0,93958.359,0,9730.2174,1083,93958.359,-2687.12</data><data>2016-07-30T01:53:52.000Z,0,4.5624095E-05,0,540.39224,0,-41872.239,14,7.501377,0,0,-0.077628593,0,1030,0,0,0,0,646575.5,7.501377,0,40530,7.501377,0,999839730,0,-18.909616,0,646575.5,0,0,0,0,1030,0,0,148411.63,0,139900,10.75167,918.70457,25115.231,0,646575.5,0,418.58718,0,0,2429.42,0,8041,0,0,0,0,0,580.75747,0,0,93958.359,0,0,0,-103370.42,0,0,162.17029,0,0,1030,0,147655,0,93958.359,0,9730.2174,1083,93958.359,3707.12</data><data>2016-07-30T01:53:54.000Z,0,4.5705175E-05,0,540.24239,0,-38211.786,14,7.501377,0,0,-0.077083991,0,1030,0,0,0,0,646575.5,7.501377,0,40532,7.501377,0,999839730,0,-19.059471,0,646575.5,0,0,0,0,1030,0,0,147270.35,0,139902,10.75167,918.70457,25115.231,0,646575.5,0,418.58718,0,0,2429.42,0,8041,0,0,0,0,0,580.75747,0,0,93958.359,0,0,0,-99970.066,0,0,162.17029,0,0,1030,0,147067,0,93958.359,0,9730.2174,1083,93958.359,-2003.01</data><data>2016-07-30T01:53:57.000Z,0,4.5686076E-05,0,540.51119,0,-47439.077,14,7.501377,0,0,-0.073262056,0,1030,0,0,0,0,646575.5,7.501377,0,40535,7.501377,0,999839730,0,-18.790665,0,646575.5,0,0,0,0,1030,0,0,141618.79,0,139905,10.75167,918.70457,25115.231,0,646575.5,0,418.58718,0,0,2429.42,0,8041,0,0,0,0,0,580.75747,0,0,93958.359,0,0,0,-97664.399,0,0,162.17029,0,0,1030,0,151443,0,93958.359,0,9730.2174,1083,93958.359,-1687.15</data><data>2016-07-30T01:54:00.000Z,0,4.5856748E-05,0,540.35566,0,-39918.016,14,7.501377,0,0,-0.084246695,0,1030,0,0,0,0,650421.7,7.501377,0,40538,7.501377,0,999839730,0,-18.946194,0,650421.7,0,0,0,0,1030,0,0,143306.37,0,139908,10.75167,918.70457,25115.231,0,646575.5,0,418.58718,0,0,2429.42,0,8041,0,0,0,0,0,580.75747,0,0,93958.359,0,0,0,-99635.057,0,0,162.17029,0,0,1030,0,149905,0,93958.359,0,9730.2174,1083,93958.359,-2687.12</data><data>2016-07-30T01:54:03.000Z,0,4.566163E-05,0,540.7878,0,-40084.421,14,7.501377,0,0,-0.079843402,0,1030,0,0,0,0,647857.57,7.501377,0,40541,7.501377,0,999839730,0,-18.514054,0,650421.7,0,0,0,0,1030,0,0,145305.16,0,139911,10.75167,918.70457,25115.231,0,646575.5,0,418.58718,0,0,2429.42,0,8041,0,0,0,0,0,580.75747,0,0,93958.359,0,0,0,-98649.471,0,0,162.17029,0,0,1030,0,152395,0,93958.359,0,9730.2174,1083,93958.359,2255.7</data><data>2016-07-30T01:54:06.000Z,0,4.5662292E-05,0,540.0778,0,-42746.375,14,7.501377,0,0,-0.084495544,0,1030,0,0,0,0,646575.5,7.501377,0,40544,7.501377,0,999839730,0,-19.224061,0,646575.5,0,0,0,0,1030,0,0,148012.7,0,139914,10.75167,918.70457,25115.231,0,646575.5,0,418.58718,0,0,2429.42,0,8041,0,0,0,0,0,580.75747,0,0,90112.159,0,0,0,-101384.87,0,0,162.17029,0,0,1030,0,145886,0,91394.226,0,9730.2174,1083,93958.359,909.06</data><data>2016-07-30T01:54:08.000Z,0,4.5801572E-05,0,540.72313,0,-44588.891,14,7.501377,0,0,-0.082705276,0,1030,0,0,0,0,643828.32,7.501377,0,40546,7.501377,0,999839730,0,-18.578726,0,646575.5,0,0,0,0,1030,0,0,145846.91,0,139916,10.75167,918.70457,25115.231,0,638883.4,0,418.58718,0,0,2429.42,0,8041,0,0,0,0,0,580.75747,0,0,90112.159,0,0,0,-98384.75,0,0,162.17029,0,0,1030,0,148724,0,90478.464,0,9730.2174,1083,90112.159,-2799.6</data><data>2016-07-30T01:54:11.000Z,0,4.5684459E-05,0,540.17958,0,-40935.445,14,7.501377,0,0,-0.074828664,0,1030,0,0,0,0,638883.4,7.501377,0,40549,7.501377,0,999839730,0,-19.122282,0,642729.5,0,0,0,0,1030,0,0,149043.62,0,139919,10.75167,918.70457,25115.231,0,638883.4,0,418.58718,0,0,2429.42,0,8041,0,0,0,0,0,580.75747,0,0,90112.159,0,0,0,-104308.24,0,0,162.17029,0,0,1030,0,150618,0,91394.226,0,9730.2174,1083,93958.359,-4583.82</data><data>2016-07-30T01:54:14.000Z,0,4.5626238E-05,0,540.60084,0,-39046.448,14,7.501377,0,0,-0.077360372,0,1030,0,0,0,0,642729.5,7.501377,0,40553,7.501377,0,999839730,0,-18.701016,0,642729.5,0,0,0,0,1030,0,0,144262.58,0,139923,10.75167,918.70457,25115.231,0,642729.5,0,418.58718,0,0,2429.42,0,8041,0,0,0,0,0,580.75747,0,0,93958.359,0,0,0,-96734.795,0,0,162.17029,0,0,1030,0,142938,0,93958.359,0,9730.2174,1083,93958.359,1691.78</data><data>2016-07-30T01:54:17.000Z,0,4.5722852E-05,0,540.02362,0,-45652.286,14,7.501377,0,0,-0.08054773,0,1030,0,0,0,0,650421.7,7.501377,0,40556,7.501377,0,999839730,0,-19.27824,0,650421.7,0,0,0,0,1030,0,0,148469.9,0,139926,10.75167,918.70457,25115.231,0,642729.5,0,418.58718,0,0,2429.42,0,8041,0,0,0,0,0,580.75747,0,0,93958.359,0,0,0,-97717.299,0,0,162.17029,0,0,1030,0,142103,0,95240.359,0,9730.2174,1083,97804.359,-3694.79</data><data>2016-07-30T01:54:20.000Z,0,4.564408E-05,0,540.78673,0,-40085.448,14,7.501377,0,0,-0.081055363,0,1030,0,0,0,0,647857.57,7.501377,0,40559,7.501377,0,999839730,0,-18.515129,0,650421.7,0,0,0,0,1030,0,0,146103.02,0,139929,10.75167,918.70457,25115.231,0,646575.5,0,418.58718,0,0,2429.42,0,8041,0,0,0,0,0,580.75747,0,0,97804.359,0,0,0,-100509.71,0,0,162.17029,0,0,1030,0,140330,0,97804.359,0,9730.2174,1083,97804.359,2816.55</data><data>2016-07-30T01:54:22.000Z,0,4.5602737E-05,0,540.38294,0,-43672.897,14,7.501377,0,0,-0.076514944,0,1030,0,0,0,0,646941.8,7.501377,0,40560,7.501377,0,999839730,0,-18.91892,0,646575.5,0,0,0,0,1030,0,0,147918.74,0,139930,10.75167,918.70457,25115.231,0,646575.5,0,418.58718,0,0,2429.42,0,8041,0,0,0,0,0,580.75747,0,0,93958.359,0,0,0,-103281.46,0,0,162.17029,0,0,1030,0,141634,0,97804.359,0,9730.2174,1083,97804.359,11891.7</data><data>2016-07-30T01:54:25.000Z,0,4.5674993E-05,0,540.56916,0,-43737.097,14,7.501377,0,0,-0.077416996,0,1030,0,0,0,0,646575.5,7.501377,0,40563,7.501377,0,999839730,0,-18.732696,0,646575.5,0,0,0,0,1030,0,0,141791.52,0,139933,10.75167,918.70457,25115.231,0,646575.5,0,418.58718,0,0,2429.42,0,8041,0,0,0,0,0,580.75747,0,0,93958.359,0,0,0,-106997.42,0,0,162.17029,0,0,1030,0,150618,0,93958.359,0,9730.2174,1083,93958.359,-2582.35</data><data>2016-07-30T01:54:28.000Z,0,4.5755089E-05,0,539.93921,0,-41979.067,14,7.501377,0,0,-0.077654918,0,1030,0,0,0,0,646575.5,7.501377,0,40566,7.501377,0,999839730,0,-19.362645,0,646575.5,0,0,0,0,1030,0,0,146209.27,0,139936,10.75167,918.70457,25115.231,0,646575.5,0,418.58718,0,0,2429.42,0,8041,0,0,0,0,0,580.75747,0,0,93958.359,0,0,0,-98686.45,0,0,162.17029,0,0,1030,0,148243,0,93958.359,0,9730.2174,1083,93958.359,-3945.94</data><data>2016-07-30T01:54:31.000Z,0,4.5588994E-05,0,540.42387,0,-39140.95,14,7.501377,0,0,-0.075675547,0,1030,0,0,0,0,642729.5,7.501377,0,40569,7.501377,0,999839730,0,-18.877983,0,646575.5,0,0,0,0,1030,0,0,149038.14,0,139939,10.75167,918.70457,25115.231,0,642729.5,0,418.58718,0,0,2429.42,0,8041,0,0,0,0,0,580.75747,0,0,93958.359,0,0,0,-105252.23,0,0,162.17029,0,0,1030,0,146004,0,93958.359,0,9730.2174,1083,93958.359,3935.15</data><data>2016-07-30T01:54:34.000Z,0,4.5732455E-05,0,539.9994,0,-42755.62,14,7.501377,0,0,-0.079964101,0,1030,0,0,0,0,645293.5,7.501377,0,40572,7.501377,0,999839730,0,-19.302457,0,646575.5,0,0,0,0,1030,0,0,146862.51,0,139942,10.75167,918.70457,25115.231,0,642729.5,0,418.58718,0,0,2429.42,0,8041,0,0,0,0,0,580.75747,0,0,93958.359,0,0,0,-105153.1,0,0,162.17029,0,0,1030,0,147776,0,93958.359,0,9730.2174,1083,97804.359,-2582.35</data><data>2016-07-30T01:54:36.000Z,0,4.5703431E-05,0,540.38956,0,-41502.268,14,7.501377,0,0,-0.076180803,0,1030,0,0,0,0,644835.64,7.501377,0,40574,7.501377,0,999839730,0,-18.912294,0,646575.5,0,0,0,0,1030,0,0,144125.1,0,139944,10.75167,918.70457,25115.231,0,642729.5,0,418.58718,0,0,2429.42,0,8041,0,0,0,0,0,580.75747,0,0,97804.359,0,0,0,-103460.26,0,0,162.17029,0,0,1030,0,139610,0,96705.502,0,9730.2174,1083,97804.359,-10178.4</data><data>2016-07-30T01:54:39.000Z,0,4.5681654E-05,0,540.31784,0,-38998.171,14,7.501377,0,0,-0.078624487,0,1030,0,0,0,0,642729.5,7.501377,0,40577,7.501377,0,999839730,0,-18.984019,0,642729.5,0,0,0,0,1030,0,0,145722.6,0,139947,10.75167,918.70457,25115.231,0,642729.5,0,418.58718,0,0,2429.42,0,8041,0,0,0,0,0,580.75747,0,0,97804.359,0,0,0,-101375.11,0,0,162.17029,0,0,1030,0,141387,0,97804.359,0,9730.2174,1083,97804.359,677.943</data><data>2016-07-30T01:54:42.000Z,0,4.5757972E-05,0,540.24559,0,-43825.948,14,7.501377,0,0,-0.079703331,0,1030,0,0,0,0,650421.7,7.501377,0,40580,7.501377,0,999839730,0,-19.056264,0,650421.7,0,0,0,0,1030,0,0,143042.47,0,139950,10.75167,918.70457,25115.231,0,650421.7,0,418.58718,0,0,2429.42,0,8041,0,0,0,0,0,580.75747,0,0,93958.359,0,0,0,-103374.02,0,0,162.17029,0,0,1030,0,147423,0,95240.359,0,9730.2174,1083,97804.359,-1665.58</data><data>2016-07-30T01:54:45.000Z,0,4.5718352E-05,0,540.34355,0,-44718.573,14,7.501377,0,0,-0.075955689,0,1030,0,0,0,0,642729.5,7.501377,0,40583,7.501377,0,999839730,0,-18.958306,0,650421.7,0,0,0,0,1030,0,0,148346.51,0,139953,10.75167,918.70457,25115.231,0,642729.5,0,418.58718,0,0,2429.42,0,8041,0,0,0,0,0,580.75747,0,0,93958.359,0,0,0,-102368.91,0,0,162.17029,0,0,1030,0,148965,0,93958.359,0,9730.2174,1083,93958.359,7303.3</data><data>2016-07-30T01:54:48.000Z,0,4.5734831E-05,0,540.12945,0,-42768.973,14,7.501377,0,0,-0.079963605,0,1030,0,0,0,0,642729.5,7.501377,0,40586,7.501377,0,999839730,0,-19.172405,0,642729.5,0,0,0,0,1030,0,0,144964.49,0,139956,10.75167,918.70457,25115.231,0,642729.5,0,418.58718,0,0,2429.42,0,8041,0,0,0,0,0,580.75747,0,0,90112.159,0,0,0,-105068.87,0,0,162.17029,0,0,1030,0,149666,0,91394.226,0,9730.2174,1083,93958.359,7303.3</data><data>2016-07-30T01:54:50.000Z,0,4.5720952E-05,0,540.37167,0,-42449.261,14,7.501377,0,0,-0.076728811,0,1030,0,0,0,0,642729.5,7.501377,0,40588,7.501377,0,999839730,0,-18.930184,0,642729.5,0,0,0,0,1030,0,0,145000.23,0,139958,10.75167,918.70457,25115.231,0,642729.5,0,418.58718,0,0,2429.42,0,8041,0,0,0,0,0,580.75747,0,0,90112.159,0,0,0,-97447.516,0,0,162.17029,0,0,1030,0,148714,0,90478.464,0,9730.2174,1083,90112.159,-2799.6</data><data>2016-07-30T01:54:53.000Z,0,4.5668974E-05,0,540.40206,0,-43817.731,14,7.501377,0,0,-0.081558526,0,1030,0,0,0,0,642729.5,7.501377,0,40591,7.501377,0,999839730,0,-18.899793,0,642729.5,0,0,0,0,1030,0,0,143562.73,0,139961,10.75167,918.70457,25115.231,0,642729.5,0,418.58718,0,0,2429.42,0,8041,0,0,0,0,0,580.75747,0,0,90112.159,0,0,0,-103361.69,0,0,162.17029,0,0,1030,0,145173,0,92676.226,0,9730.2174,1083,97804.359,-1779.6</data><data>2016-07-30T01:54:56.000Z,0,4.5657092E-05,0,540.48833,0,-41890.728,14,7.501377,0,0,-0.080712636,0,1030,0,0,0,0,642729.5,7.501377,0,40594,7.501377,0,999839730,0,-18.813532,0,642729.5,0,0,0,0,1030,0,0,142365.25,0,139964,10.75167,918.70457,25115.231,0,642729.5,0,418.58718,0,0,2429.42,0,8041,0,0,0,0,0,580.75747,0,0,97804.359,0,0,0,-104118.73,0,0,162.17029,0,0,1030,0,147893,0,97804.359,0,9730.2174,1083,97804.359,-3919.74</data><data>2016-07-30T01:54:59.000Z,0,4.5647859E-05,0,540.1864,0,-39041.313,14,7.501377,0,0,-0.081437826,0,1030,0,0,0,0,642729.5,7.501377,0,40597,7.501377,0,999839730,0,-19.115457,0,642729.5,0,0,0,0,1030,0,0,144908.96,0,139967,10.75167,918.70457,25115.231,0,642729.5,0,418.58718,0,0,2429.42,0,8041,0,0,0,0,0,580.75747,0,0,97804.359,0,0,0,-98620.196,0,0,162.17029,0,0,1030,0,146121,0,97804.359,0,9730.2174,1083,97804.359,-10178.4</data><data>2016-07-30T01:55:02.000Z,0,4.5747453E-05,0,540.44261,0,-39163.548,14,7.501377,0,0,-0.084246695,0,1030,0,0,0,0,645293.5,7.501377,0,40600,7.501377,0,999839730,0,-18.85925,0,646575.5,0,0,0,0,1030,0,0,147317.65,0,139970,10.75167,918.70457,25115.231,0,642729.5,0,418.58718,0,0,2429.42,0,8041,0,0,0,0,0,580.75747,0,0,97804.359,0,0,0,-100550.28,0,0,162.17029,0,0,1030,0,152496,0,97804.359,0,9730.2174,1083,97804.359,-5609.98</data><data>2016-07-30T01:55:04.000Z,0,4.5673991E-05,0,540.04404,0,-44339.468,14,7.501377,0,0,-0.07805473,0,1030,0,0,0,0,646209.21,7.501377,0,40602,7.501377,0,999839730,0,-19.257816,0,646575.5,0,0,0,0,1030,0,0,145686.51,0,139972,10.75167,918.70457,25115.231,0,646575.5,0,418.58718,0,0,2429.42,0,8041,0,0,0,0,0,580.75747,0,0,97804.359,0,0,0,-96201.612,0,0,162.17029,0,0,1030,0,146121,0,97804.359,0,9730.2174,1083,97804.359,5851.88</data><data>2016-07-30T01:55:07.000Z,0,4.5606213E-05,0,540.46801,0,-41074.115,14,7.501377,0,0,-0.08007884,0,1030,0,0,0,0,646575.5,7.501377,0,40605,7.501377,0,999839730,0,-18.833849,0,646575.5,0,0,0,0,1030,0,0,144069.97,0,139975,10.75167,918.70457,25115.231,0,646575.5,0,418.58718,0,0,2429.42,0,8041,0,0,0,0,0,580.75747,0,0,97804.359,0,0,0,-104159.3,0,0,162.17029,0,0,1030,0,145765,0,97804.359,0,9730.2174,1083,97804.359,1805.79</data><data>2016-07-30T01:55:10.000Z,0,4.5630192E-05,0,540.49266,0,-50292.602,14,7.501377,0,0,-0.076951583,0,1030,0,0,0,0,646575.5,7.501377,0,40608,7.501377,0,999839730,0,-18.809193,0,646575.5,0,0,0,0,1030,0,0,140451.46,0,139978,10.75167,918.70457,25115.231,0,642729.5,0,418.58718,0,0,2429.42,0,8041,0,0,0,0,0,580.75747,0,0,93958.359,0,0,0,-102350.42,0,0,162.17029,0,0,1030,0,146952,0,97804.359,0,9730.2174,1083,97804.359,-2799.6</data><data>2016-07-30T01:55:13.000Z,0,4.581555E-05,0,540.50706,0,-44549.088,0,7.501377,0,0,-0.075155497,0,1030,0,0,0,0,642729.5,7.501377,0,40608,7.501377,0,999839730,0,-18.794802,0,642729.5,0,0,0,0,1030,0,0,143066.47,0,139978,10.75167,918.70457,25115.231,0,642729.5,0,418.58718,0,0,2429.42,0,8041,0,0,0,0,0,580.75747,0,0,93958.359,0,0,0,-104275.89,0,0,162.17029,0,0,1030,0,145535,0,93958.359,0,9730.2174,1083,93958.359,-1779.6</data></logData><commonData><sourceName>Baker Hughes</sourceName><dTimCreation>2016-07-28T13:46:27.536Z</dTimCreation><dTimLastChange>2016-07-30T02:57:56.472Z</dTimLastChange><itemState>actual</itemState><priv_objectGrowing>false</priv_objectGrowing><priv_userLastChange>RealtimeManager</priv_userLastChange><priv_ipLastChange>WS530</priv_ipLastChange><priv_userOwner>sc-sync-bhi</priv_userOwner><priv_ipOwner>143.97.229.4</priv_ipOwner><priv_dTimReceived>2016-07-28T13:46:27.536Z</priv_dTimReceived></commonData><customData><feed>2.1.7254.1</feed><advantage>2.2U4</advantage></customData></log></logs>